{
  "algorithm": "DynaQ",
  "state_space_size": 25,
  "action_space_size": 4,
  "learning_rate": 0.1,
  "gamma": 0.99,
  "epsilon": 0.027012904489336704,
  "epsilon_decay": 0.998,
  "epsilon_min": 0.02,
  "n_planning_steps": 10,
  "is_trained": true,
  "q_function": [
    [
      0.9227446944279158,
      0.9320653479069863,
      0.9227446944279158,
      0.9320653479069863
    ],
    [
      0.9320653479069863,
      0.9414801494009968,
      0.9227446944279158,
      0.9414801494009968
    ],
    [
      0.9414801494009968,
      0.9509900498999972,
      0.9320653479069863,
      0.9509900498999972
    ],
    [
      0.9509900498999972,
      0.9605960099999977,
      0.9414801494009968,
      -2.9999999999999982
    ],
    [
      0.0,
      0.0,
      0.0,
      0.0
    ],
    [
      0.9227446944279158,
      0.9414801494009968,
      0.9320653479069863,
      0.9414801494009968
    ],
    [
      0.9320653479069863,
      0.9509900498999972,
      0.9320653479069863,
      0.9509900498999972
    ],
    [
      0.9414801494009968,
      0.9605960099999977,
      0.9414801494009968,
      0.9605960099999977
    ],
    [
      0.9509900498999972,
      0.9702989999999982,
      0.9509900498999972,
      0.9702989999999982
    ],
    [
      -2.9999999999999982,
      0.9800999999999986,
      0.9605960099999977,
      0.9702989999999982
    ],
    [
      0.9320653479069863,
      0.9320653479069863,
      0.9414801494009968,
      0.9509900498999972
    ],
    [
      0.9414801494009968,
      0.9414801494009968,
      0.9414801494009968,
      0.9605960099999977
    ],
    [
      0.9509900498999972,
      0.9509900498999972,
      0.9509900498999972,
      0.9702989999999982
    ],
    [
      0.9605960099999977,
      0.9800999999999986,
      0.9605960099999977,
      0.9800999999999986
    ],
    [
      0.9702989999999982,
      0.9899999999999991,
      0.9702989999999982,
      0.9800999999999986
    ],
    [
      0.9414801494009968,
      0.0,
      0.0,
      0.0
    ],
    [
      0.9509900498999972,
      0.0,
      0.0,
      0.0
    ],
    [
      0.9605960099999977,
      0.9414801494009968,
      0.9414801439375989,
      0.0
    ],
    [
      0.9702989999999982,
      0.9702989999986754,
      0.9509900498999972,
      0.9899999999999991
    ],
    [
      0.9800999999999986,
      0.9999999999999996,
      0.9800999999999986,
      0.9899999999999991
    ],
    [
      0.0,
      0.0,
      0.0,
      0.0
    ],
    [
      0.0,
      0.0,
      0.0,
      0.0
    ],
    [
      0.9509900498999972,
      0.0,
      0.0,
      0.0
    ],
    [
      0.9800999999999739,
      0.0,
      0.0,
      0.0
    ],
    [
      0.0,
      0.0,
      0.0,
      0.0
    ]
  ],
  "model": {
    "0_0": {
      "next_state": 0,
      "reward": 0.0
    },
    "0_2": {
      "next_state": 0,
      "reward": 0.0
    },
    "0_1": {
      "next_state": 5,
      "reward": 0.0
    },
    "5_0": {
      "next_state": 0,
      "reward": 0.0
    },
    "0_3": {
      "next_state": 1,
      "reward": 0.0
    },
    "1_0": {
      "next_state": 1,
      "reward": 0.0
    },
    "1_2": {
      "next_state": 0,
      "reward": 0.0
    },
    "5_2": {
      "next_state": 5,
      "reward": 0.0
    },
    "1_3": {
      "next_state": 2,
      "reward": 0.0
    },
    "2_0": {
      "next_state": 2,
      "reward": 0.0
    },
    "2_1": {
      "next_state": 7,
      "reward": 0.0
    },
    "7_0": {
      "next_state": 2,
      "reward": 0.0
    },
    "2_2": {
      "next_state": 1,
      "reward": 0.0
    },
    "5_1": {
      "next_state": 10,
      "reward": 0.0
    },
    "10_0": {
      "next_state": 5,
      "reward": 0.0
    },
    "2_3": {
      "next_state": 3,
      "reward": 0.0
    },
    "3_0": {
      "next_state": 3,
      "reward": 0.0
    },
    "3_1": {
      "next_state": 8,
      "reward": 0.0
    },
    "8_0": {
      "next_state": 3,
      "reward": 0.0
    },
    "3_2": {
      "next_state": 2,
      "reward": 0.0
    },
    "3_3": {
      "next_state": 4,
      "reward": -3.0
    },
    "10_3": {
      "next_state": 11,
      "reward": 0.0
    },
    "11_0": {
      "next_state": 6,
      "reward": 0.0
    },
    "6_0": {
      "next_state": 1,
      "reward": 0.0
    },
    "7_3": {
      "next_state": 8,
      "reward": 0.0
    },
    "1_1": {
      "next_state": 6,
      "reward": 0.0
    },
    "7_2": {
      "next_state": 6,
      "reward": 0.0
    },
    "6_2": {
      "next_state": 5,
      "reward": 0.0
    },
    "8_3": {
      "next_state": 9,
      "reward": 0.0
    },
    "9_0": {
      "next_state": 4,
      "reward": -3.0
    },
    "6_3": {
      "next_state": 7,
      "reward": 0.0
    },
    "5_3": {
      "next_state": 6,
      "reward": 0.0
    },
    "7_1": {
      "next_state": 12,
      "reward": 0.0
    },
    "12_0": {
      "next_state": 7,
      "reward": 0.0
    },
    "8_2": {
      "next_state": 7,
      "reward": 0.0
    },
    "6_1": {
      "next_state": 11,
      "reward": 0.0
    },
    "12_1": {
      "next_state": 17,
      "reward": 0.0
    },
    "17_1": {
      "next_state": 22,
      "reward": 0.0
    },
    "22_0": {
      "next_state": 17,
      "reward": 0.0
    },
    "17_0": {
      "next_state": 12,
      "reward": 0.0
    },
    "8_1": {
      "next_state": 13,
      "reward": 0.0
    },
    "13_3": {
      "next_state": 14,
      "reward": 0.0
    },
    "14_2": {
      "next_state": 13,
      "reward": 0.0
    },
    "13_0": {
      "next_state": 8,
      "reward": 0.0
    },
    "9_1": {
      "next_state": 14,
      "reward": 0.0
    },
    "14_1": {
      "next_state": 19,
      "reward": 0.0
    },
    "19_0": {
      "next_state": 14,
      "reward": 0.0
    },
    "14_0": {
      "next_state": 9,
      "reward": 0.0
    },
    "9_3": {
      "next_state": 9,
      "reward": 0.0
    },
    "14_3": {
      "next_state": 14,
      "reward": 0.0
    },
    "10_1": {
      "next_state": 15,
      "reward": 0.0
    },
    "15_0": {
      "next_state": 10,
      "reward": 0.0
    },
    "10_2": {
      "next_state": 10,
      "reward": 0.0
    },
    "12_3": {
      "next_state": 13,
      "reward": 0.0
    },
    "9_2": {
      "next_state": 8,
      "reward": 0.0
    },
    "11_1": {
      "next_state": 16,
      "reward": 0.0
    },
    "16_0": {
      "next_state": 11,
      "reward": 0.0
    },
    "12_2": {
      "next_state": 11,
      "reward": 0.0
    },
    "11_2": {
      "next_state": 10,
      "reward": 0.0
    },
    "19_2": {
      "next_state": 18,
      "reward": 0.0
    },
    "18_0": {
      "next_state": 13,
      "reward": 0.0
    },
    "11_3": {
      "next_state": 12,
      "reward": 0.0
    },
    "19_1": {
      "next_state": 24,
      "reward": 1.0
    },
    "13_2": {
      "next_state": 12,
      "reward": 0.0
    },
    "13_1": {
      "next_state": 18,
      "reward": 0.0
    },
    "18_3": {
      "next_state": 19,
      "reward": 0.0
    },
    "19_3": {
      "next_state": 19,
      "reward": 0.0
    },
    "18_2": {
      "next_state": 17,
      "reward": 0.0
    },
    "18_1": {
      "next_state": 23,
      "reward": 0.0
    },
    "23_0": {
      "next_state": 18,
      "reward": 0.0
    },
    "17_2": {
      "next_state": 16,
      "reward": 0.0
    }
  },
  "observed_sa_pairs": [
    {
      "state": 12,
      "action": 1
    },
    {
      "state": 3,
      "action": 1
    },
    {
      "state": 17,
      "action": 0
    },
    {
      "state": 14,
      "action": 1
    },
    {
      "state": 5,
      "action": 1
    },
    {
      "state": 8,
      "action": 0
    },
    {
      "state": 19,
      "action": 0
    },
    {
      "state": 9,
      "action": 2
    },
    {
      "state": 0,
      "action": 2
    },
    {
      "state": 10,
      "action": 0
    },
    {
      "state": 8,
      "action": 3
    },
    {
      "state": 11,
      "action": 2
    },
    {
      "state": 19,
      "action": 3
    },
    {
      "state": 2,
      "action": 2
    },
    {
      "state": 1,
      "action": 0
    },
    {
      "state": 10,
      "action": 3
    },
    {
      "state": 13,
      "action": 2
    },
    {
      "state": 1,
      "action": 3
    },
    {
      "state": 6,
      "action": 2
    },
    {
      "state": 7,
      "action": 1
    },
    {
      "state": 18,
      "action": 1
    },
    {
      "state": 12,
      "action": 0
    },
    {
      "state": 23,
      "action": 0
    },
    {
      "state": 12,
      "action": 3
    },
    {
      "state": 3,
      "action": 0
    },
    {
      "state": 14,
      "action": 0
    },
    {
      "state": 3,
      "action": 3
    },
    {
      "state": 5,
      "action": 0
    },
    {
      "state": 14,
      "action": 3
    },
    {
      "state": 17,
      "action": 2
    },
    {
      "state": 5,
      "action": 3
    },
    {
      "state": 8,
      "action": 2
    },
    {
      "state": 19,
      "action": 2
    },
    {
      "state": 9,
      "action": 1
    },
    {
      "state": 10,
      "action": 2
    },
    {
      "state": 19,
      "action": 1
    },
    {
      "state": 0,
      "action": 1
    },
    {
      "state": 11,
      "action": 1
    },
    {
      "state": 1,
      "action": 2
    },
    {
      "state": 2,
      "action": 1
    },
    {
      "state": 16,
      "action": 0
    },
    {
      "state": 13,
      "action": 1
    },
    {
      "state": 6,
      "action": 1
    },
    {
      "state": 7,
      "action": 0
    },
    {
      "state": 18,
      "action": 0
    },
    {
      "state": 7,
      "action": 3
    },
    {
      "state": 18,
      "action": 3
    },
    {
      "state": 12,
      "action": 2
    },
    {
      "state": 22,
      "action": 0
    },
    {
      "state": 3,
      "action": 2
    },
    {
      "state": 14,
      "action": 2
    },
    {
      "state": 5,
      "action": 2
    },
    {
      "state": 9,
      "action": 0
    },
    {
      "state": 17,
      "action": 1
    },
    {
      "state": 9,
      "action": 3
    },
    {
      "state": 0,
      "action": 0
    },
    {
      "state": 11,
      "action": 0
    },
    {
      "state": 8,
      "action": 1
    },
    {
      "state": 1,
      "action": 1
    },
    {
      "state": 0,
      "action": 3
    },
    {
      "state": 2,
      "action": 0
    },
    {
      "state": 13,
      "action": 0
    },
    {
      "state": 10,
      "action": 1
    },
    {
      "state": 11,
      "action": 3
    },
    {
      "state": 2,
      "action": 3
    },
    {
      "state": 13,
      "action": 3
    },
    {
      "state": 15,
      "action": 0
    },
    {
      "state": 7,
      "action": 2
    },
    {
      "state": 6,
      "action": 0
    },
    {
      "state": 18,
      "action": 2
    },
    {
      "state": 6,
      "action": 3
    }
  ],
  "training_history": [
    {
      "episode": 1,
      "reward": -3.0,
      "steps": 301
    },
    {
      "episode": 2,
      "reward": -3.0,
      "steps": 74
    },
    {
      "episode": 3,
      "reward": -3.0,
      "steps": 86
    },
    {
      "episode": 4,
      "reward": -3.0,
      "steps": 86
    },
    {
      "episode": 5,
      "reward": -3.0,
      "steps": 357
    },
    {
      "episode": 6,
      "reward": -3.0,
      "steps": 57
    },
    {
      "episode": 7,
      "reward": -3.0,
      "steps": 315
    },
    {
      "episode": 8,
      "reward": -3.0,
      "steps": 21
    },
    {
      "episode": 9,
      "reward": -3.0,
      "steps": 43
    },
    {
      "episode": 10,
      "reward": -3.0,
      "steps": 209
    },
    {
      "episode": 11,
      "reward": -3.0,
      "steps": 177
    },
    {
      "episode": 12,
      "reward": -3.0,
      "steps": 96
    },
    {
      "episode": 13,
      "reward": -3.0,
      "steps": 148
    },
    {
      "episode": 14,
      "reward": -3.0,
      "steps": 158
    },
    {
      "episode": 15,
      "reward": -3.0,
      "steps": 356
    },
    {
      "episode": 16,
      "reward": -3.0,
      "steps": 195
    },
    {
      "episode": 17,
      "reward": -3.0,
      "steps": 82
    },
    {
      "episode": 18,
      "reward": -3.0,
      "steps": 20
    },
    {
      "episode": 19,
      "reward": -3.0,
      "steps": 575
    },
    {
      "episode": 20,
      "reward": -3.0,
      "steps": 114
    },
    {
      "episode": 21,
      "reward": -3.0,
      "steps": 70
    },
    {
      "episode": 22,
      "reward": -3.0,
      "steps": 115
    },
    {
      "episode": 23,
      "reward": -3.0,
      "steps": 288
    },
    {
      "episode": 24,
      "reward": -3.0,
      "steps": 318
    },
    {
      "episode": 25,
      "reward": -3.0,
      "steps": 362
    },
    {
      "episode": 26,
      "reward": -3.0,
      "steps": 79
    },
    {
      "episode": 27,
      "reward": -3.0,
      "steps": 277
    },
    {
      "episode": 28,
      "reward": -3.0,
      "steps": 38
    },
    {
      "episode": 29,
      "reward": -3.0,
      "steps": 209
    },
    {
      "episode": 30,
      "reward": -3.0,
      "steps": 102
    },
    {
      "episode": 31,
      "reward": -3.0,
      "steps": 380
    },
    {
      "episode": 32,
      "reward": -3.0,
      "steps": 150
    },
    {
      "episode": 33,
      "reward": -3.0,
      "steps": 97
    },
    {
      "episode": 34,
      "reward": -3.0,
      "steps": 40
    },
    {
      "episode": 35,
      "reward": -3.0,
      "steps": 175
    },
    {
      "episode": 36,
      "reward": -3.0,
      "steps": 418
    },
    {
      "episode": 37,
      "reward": -3.0,
      "steps": 267
    },
    {
      "episode": 38,
      "reward": -3.0,
      "steps": 99
    },
    {
      "episode": 39,
      "reward": -3.0,
      "steps": 116
    },
    {
      "episode": 40,
      "reward": -3.0,
      "steps": 173
    },
    {
      "episode": 41,
      "reward": -3.0,
      "steps": 74
    },
    {
      "episode": 42,
      "reward": -3.0,
      "steps": 532
    },
    {
      "episode": 43,
      "reward": -3.0,
      "steps": 215
    },
    {
      "episode": 44,
      "reward": -3.0,
      "steps": 82
    },
    {
      "episode": 45,
      "reward": -3.0,
      "steps": 479
    },
    {
      "episode": 46,
      "reward": -3.0,
      "steps": 164
    },
    {
      "episode": 47,
      "reward": -3.0,
      "steps": 110
    },
    {
      "episode": 48,
      "reward": -3.0,
      "steps": 614
    },
    {
      "episode": 49,
      "reward": -3.0,
      "steps": 74
    },
    {
      "episode": 50,
      "reward": -3.0,
      "steps": 165
    },
    {
      "episode": 51,
      "reward": -3.0,
      "steps": 84
    },
    {
      "episode": 52,
      "reward": -3.0,
      "steps": 30
    },
    {
      "episode": 53,
      "reward": -3.0,
      "steps": 43
    },
    {
      "episode": 54,
      "reward": -3.0,
      "steps": 207
    },
    {
      "episode": 55,
      "reward": -3.0,
      "steps": 93
    },
    {
      "episode": 56,
      "reward": -3.0,
      "steps": 65
    },
    {
      "episode": 57,
      "reward": -3.0,
      "steps": 132
    },
    {
      "episode": 58,
      "reward": -3.0,
      "steps": 128
    },
    {
      "episode": 59,
      "reward": -3.0,
      "steps": 79
    },
    {
      "episode": 60,
      "reward": -3.0,
      "steps": 232
    },
    {
      "episode": 61,
      "reward": -3.0,
      "steps": 79
    },
    {
      "episode": 62,
      "reward": -3.0,
      "steps": 347
    },
    {
      "episode": 63,
      "reward": -3.0,
      "steps": 53
    },
    {
      "episode": 64,
      "reward": -3.0,
      "steps": 301
    },
    {
      "episode": 65,
      "reward": -3.0,
      "steps": 167
    },
    {
      "episode": 66,
      "reward": -3.0,
      "steps": 48
    },
    {
      "episode": 67,
      "reward": -3.0,
      "steps": 128
    },
    {
      "episode": 68,
      "reward": -3.0,
      "steps": 28
    },
    {
      "episode": 69,
      "reward": -3.0,
      "steps": 177
    },
    {
      "episode": 70,
      "reward": -3.0,
      "steps": 423
    },
    {
      "episode": 71,
      "reward": -3.0,
      "steps": 165
    },
    {
      "episode": 72,
      "reward": -3.0,
      "steps": 83
    },
    {
      "episode": 73,
      "reward": 0.0,
      "steps": 1000
    },
    {
      "episode": 74,
      "reward": -3.0,
      "steps": 540
    },
    {
      "episode": 75,
      "reward": -3.0,
      "steps": 68
    },
    {
      "episode": 76,
      "reward": -3.0,
      "steps": 232
    },
    {
      "episode": 77,
      "reward": -3.0,
      "steps": 142
    },
    {
      "episode": 78,
      "reward": -3.0,
      "steps": 149
    },
    {
      "episode": 79,
      "reward": -3.0,
      "steps": 82
    },
    {
      "episode": 80,
      "reward": -3.0,
      "steps": 287
    },
    {
      "episode": 81,
      "reward": -3.0,
      "steps": 406
    },
    {
      "episode": 82,
      "reward": -3.0,
      "steps": 149
    },
    {
      "episode": 83,
      "reward": -3.0,
      "steps": 354
    },
    {
      "episode": 84,
      "reward": -3.0,
      "steps": 242
    },
    {
      "episode": 85,
      "reward": -3.0,
      "steps": 233
    },
    {
      "episode": 86,
      "reward": -3.0,
      "steps": 145
    },
    {
      "episode": 87,
      "reward": -3.0,
      "steps": 553
    },
    {
      "episode": 88,
      "reward": -3.0,
      "steps": 221
    },
    {
      "episode": 89,
      "reward": -3.0,
      "steps": 215
    },
    {
      "episode": 90,
      "reward": -3.0,
      "steps": 711
    },
    {
      "episode": 91,
      "reward": -3.0,
      "steps": 410
    },
    {
      "episode": 92,
      "reward": 0.0,
      "steps": 1000
    },
    {
      "episode": 93,
      "reward": -3.0,
      "steps": 321
    },
    {
      "episode": 94,
      "reward": -3.0,
      "steps": 882
    },
    {
      "episode": 95,
      "reward": -3.0,
      "steps": 103
    },
    {
      "episode": 96,
      "reward": -3.0,
      "steps": 451
    },
    {
      "episode": 97,
      "reward": -3.0,
      "steps": 221
    },
    {
      "episode": 98,
      "reward": -3.0,
      "steps": 87
    },
    {
      "episode": 99,
      "reward": -3.0,
      "steps": 202
    },
    {
      "episode": 100,
      "reward": -3.0,
      "steps": 151
    },
    {
      "episode": 101,
      "reward": -3.0,
      "steps": 139
    },
    {
      "episode": 102,
      "reward": -3.0,
      "steps": 244
    },
    {
      "episode": 103,
      "reward": -3.0,
      "steps": 53
    },
    {
      "episode": 104,
      "reward": -3.0,
      "steps": 348
    },
    {
      "episode": 105,
      "reward": -3.0,
      "steps": 116
    },
    {
      "episode": 106,
      "reward": -3.0,
      "steps": 24
    },
    {
      "episode": 107,
      "reward": -3.0,
      "steps": 199
    },
    {
      "episode": 108,
      "reward": -3.0,
      "steps": 183
    },
    {
      "episode": 109,
      "reward": -3.0,
      "steps": 48
    },
    {
      "episode": 110,
      "reward": -3.0,
      "steps": 280
    },
    {
      "episode": 111,
      "reward": -3.0,
      "steps": 164
    },
    {
      "episode": 112,
      "reward": -3.0,
      "steps": 197
    },
    {
      "episode": 113,
      "reward": -3.0,
      "steps": 263
    },
    {
      "episode": 114,
      "reward": -3.0,
      "steps": 955
    },
    {
      "episode": 115,
      "reward": -3.0,
      "steps": 250
    },
    {
      "episode": 116,
      "reward": -3.0,
      "steps": 178
    },
    {
      "episode": 117,
      "reward": -3.0,
      "steps": 784
    },
    {
      "episode": 118,
      "reward": -3.0,
      "steps": 174
    },
    {
      "episode": 119,
      "reward": -3.0,
      "steps": 228
    },
    {
      "episode": 120,
      "reward": -3.0,
      "steps": 326
    },
    {
      "episode": 121,
      "reward": -3.0,
      "steps": 128
    },
    {
      "episode": 122,
      "reward": -3.0,
      "steps": 74
    },
    {
      "episode": 123,
      "reward": -3.0,
      "steps": 373
    },
    {
      "episode": 124,
      "reward": -3.0,
      "steps": 121
    },
    {
      "episode": 125,
      "reward": -3.0,
      "steps": 38
    },
    {
      "episode": 126,
      "reward": -3.0,
      "steps": 120
    },
    {
      "episode": 127,
      "reward": -3.0,
      "steps": 189
    },
    {
      "episode": 128,
      "reward": -3.0,
      "steps": 477
    },
    {
      "episode": 129,
      "reward": -3.0,
      "steps": 364
    },
    {
      "episode": 130,
      "reward": -3.0,
      "steps": 185
    },
    {
      "episode": 131,
      "reward": -3.0,
      "steps": 441
    },
    {
      "episode": 132,
      "reward": -3.0,
      "steps": 845
    },
    {
      "episode": 133,
      "reward": -3.0,
      "steps": 248
    },
    {
      "episode": 134,
      "reward": -3.0,
      "steps": 406
    },
    {
      "episode": 135,
      "reward": -3.0,
      "steps": 462
    },
    {
      "episode": 136,
      "reward": -3.0,
      "steps": 79
    },
    {
      "episode": 137,
      "reward": -3.0,
      "steps": 139
    },
    {
      "episode": 138,
      "reward": -3.0,
      "steps": 258
    },
    {
      "episode": 139,
      "reward": -3.0,
      "steps": 70
    },
    {
      "episode": 140,
      "reward": -3.0,
      "steps": 469
    },
    {
      "episode": 141,
      "reward": -3.0,
      "steps": 451
    },
    {
      "episode": 142,
      "reward": -3.0,
      "steps": 285
    },
    {
      "episode": 143,
      "reward": -3.0,
      "steps": 49
    },
    {
      "episode": 144,
      "reward": -3.0,
      "steps": 308
    },
    {
      "episode": 145,
      "reward": 0.0,
      "steps": 1000
    },
    {
      "episode": 146,
      "reward": -3.0,
      "steps": 505
    },
    {
      "episode": 147,
      "reward": -3.0,
      "steps": 310
    },
    {
      "episode": 148,
      "reward": -3.0,
      "steps": 196
    },
    {
      "episode": 149,
      "reward": -3.0,
      "steps": 86
    },
    {
      "episode": 150,
      "reward": -3.0,
      "steps": 329
    },
    {
      "episode": 151,
      "reward": -3.0,
      "steps": 140
    },
    {
      "episode": 152,
      "reward": -3.0,
      "steps": 301
    },
    {
      "episode": 153,
      "reward": -3.0,
      "steps": 51
    },
    {
      "episode": 154,
      "reward": -3.0,
      "steps": 733
    },
    {
      "episode": 155,
      "reward": -3.0,
      "steps": 144
    },
    {
      "episode": 156,
      "reward": -3.0,
      "steps": 388
    },
    {
      "episode": 157,
      "reward": -3.0,
      "steps": 565
    },
    {
      "episode": 158,
      "reward": -3.0,
      "steps": 70
    },
    {
      "episode": 159,
      "reward": -3.0,
      "steps": 305
    },
    {
      "episode": 160,
      "reward": -3.0,
      "steps": 473
    },
    {
      "episode": 161,
      "reward": -3.0,
      "steps": 116
    },
    {
      "episode": 162,
      "reward": -3.0,
      "steps": 361
    },
    {
      "episode": 163,
      "reward": -3.0,
      "steps": 351
    },
    {
      "episode": 164,
      "reward": -3.0,
      "steps": 63
    },
    {
      "episode": 165,
      "reward": -3.0,
      "steps": 184
    },
    {
      "episode": 166,
      "reward": -3.0,
      "steps": 120
    },
    {
      "episode": 167,
      "reward": -3.0,
      "steps": 61
    },
    {
      "episode": 168,
      "reward": -3.0,
      "steps": 408
    },
    {
      "episode": 169,
      "reward": -3.0,
      "steps": 778
    },
    {
      "episode": 170,
      "reward": -3.0,
      "steps": 390
    },
    {
      "episode": 171,
      "reward": -3.0,
      "steps": 372
    },
    {
      "episode": 172,
      "reward": -3.0,
      "steps": 110
    },
    {
      "episode": 173,
      "reward": -3.0,
      "steps": 250
    },
    {
      "episode": 174,
      "reward": -3.0,
      "steps": 291
    },
    {
      "episode": 175,
      "reward": -3.0,
      "steps": 20
    },
    {
      "episode": 176,
      "reward": -3.0,
      "steps": 64
    },
    {
      "episode": 177,
      "reward": -3.0,
      "steps": 272
    },
    {
      "episode": 178,
      "reward": -3.0,
      "steps": 391
    },
    {
      "episode": 179,
      "reward": -3.0,
      "steps": 159
    },
    {
      "episode": 180,
      "reward": -3.0,
      "steps": 107
    },
    {
      "episode": 181,
      "reward": -3.0,
      "steps": 116
    },
    {
      "episode": 182,
      "reward": -3.0,
      "steps": 210
    },
    {
      "episode": 183,
      "reward": -3.0,
      "steps": 213
    },
    {
      "episode": 184,
      "reward": -3.0,
      "steps": 745
    },
    {
      "episode": 185,
      "reward": -3.0,
      "steps": 129
    },
    {
      "episode": 186,
      "reward": -3.0,
      "steps": 641
    },
    {
      "episode": 187,
      "reward": -3.0,
      "steps": 95
    },
    {
      "episode": 188,
      "reward": -3.0,
      "steps": 142
    },
    {
      "episode": 189,
      "reward": -3.0,
      "steps": 136
    },
    {
      "episode": 190,
      "reward": -3.0,
      "steps": 87
    },
    {
      "episode": 191,
      "reward": -3.0,
      "steps": 184
    },
    {
      "episode": 192,
      "reward": -3.0,
      "steps": 48
    },
    {
      "episode": 193,
      "reward": -3.0,
      "steps": 340
    },
    {
      "episode": 194,
      "reward": -3.0,
      "steps": 397
    },
    {
      "episode": 195,
      "reward": -3.0,
      "steps": 58
    },
    {
      "episode": 196,
      "reward": -3.0,
      "steps": 105
    },
    {
      "episode": 197,
      "reward": -3.0,
      "steps": 117
    },
    {
      "episode": 198,
      "reward": -3.0,
      "steps": 249
    },
    {
      "episode": 199,
      "reward": -3.0,
      "steps": 136
    },
    {
      "episode": 200,
      "reward": -3.0,
      "steps": 537
    },
    {
      "episode": 201,
      "reward": -3.0,
      "steps": 924
    },
    {
      "episode": 202,
      "reward": -3.0,
      "steps": 273
    },
    {
      "episode": 203,
      "reward": -3.0,
      "steps": 101
    },
    {
      "episode": 204,
      "reward": -3.0,
      "steps": 685
    },
    {
      "episode": 205,
      "reward": -3.0,
      "steps": 262
    },
    {
      "episode": 206,
      "reward": -3.0,
      "steps": 253
    },
    {
      "episode": 207,
      "reward": -3.0,
      "steps": 903
    },
    {
      "episode": 208,
      "reward": -3.0,
      "steps": 62
    },
    {
      "episode": 209,
      "reward": -3.0,
      "steps": 167
    },
    {
      "episode": 210,
      "reward": -3.0,
      "steps": 589
    },
    {
      "episode": 211,
      "reward": -3.0,
      "steps": 387
    },
    {
      "episode": 212,
      "reward": -3.0,
      "steps": 412
    },
    {
      "episode": 213,
      "reward": -3.0,
      "steps": 502
    },
    {
      "episode": 214,
      "reward": -3.0,
      "steps": 182
    },
    {
      "episode": 215,
      "reward": -3.0,
      "steps": 101
    },
    {
      "episode": 216,
      "reward": -3.0,
      "steps": 94
    },
    {
      "episode": 217,
      "reward": -3.0,
      "steps": 114
    },
    {
      "episode": 218,
      "reward": -3.0,
      "steps": 117
    },
    {
      "episode": 219,
      "reward": -3.0,
      "steps": 356
    },
    {
      "episode": 220,
      "reward": -3.0,
      "steps": 248
    },
    {
      "episode": 221,
      "reward": -3.0,
      "steps": 404
    },
    {
      "episode": 222,
      "reward": -3.0,
      "steps": 228
    },
    {
      "episode": 223,
      "reward": -3.0,
      "steps": 546
    },
    {
      "episode": 224,
      "reward": -3.0,
      "steps": 98
    },
    {
      "episode": 225,
      "reward": -3.0,
      "steps": 339
    },
    {
      "episode": 226,
      "reward": -3.0,
      "steps": 186
    },
    {
      "episode": 227,
      "reward": -3.0,
      "steps": 210
    },
    {
      "episode": 228,
      "reward": -3.0,
      "steps": 298
    },
    {
      "episode": 229,
      "reward": -3.0,
      "steps": 456
    },
    {
      "episode": 230,
      "reward": -3.0,
      "steps": 81
    },
    {
      "episode": 231,
      "reward": -3.0,
      "steps": 621
    },
    {
      "episode": 232,
      "reward": -3.0,
      "steps": 116
    },
    {
      "episode": 233,
      "reward": -3.0,
      "steps": 591
    },
    {
      "episode": 234,
      "reward": -3.0,
      "steps": 209
    },
    {
      "episode": 235,
      "reward": -3.0,
      "steps": 74
    },
    {
      "episode": 236,
      "reward": -3.0,
      "steps": 215
    },
    {
      "episode": 237,
      "reward": -3.0,
      "steps": 611
    },
    {
      "episode": 238,
      "reward": -3.0,
      "steps": 198
    },
    {
      "episode": 239,
      "reward": -3.0,
      "steps": 340
    },
    {
      "episode": 240,
      "reward": -3.0,
      "steps": 154
    },
    {
      "episode": 241,
      "reward": -3.0,
      "steps": 331
    },
    {
      "episode": 242,
      "reward": -3.0,
      "steps": 243
    },
    {
      "episode": 243,
      "reward": -3.0,
      "steps": 104
    },
    {
      "episode": 244,
      "reward": -3.0,
      "steps": 261
    },
    {
      "episode": 245,
      "reward": -3.0,
      "steps": 66
    },
    {
      "episode": 246,
      "reward": -3.0,
      "steps": 623
    },
    {
      "episode": 247,
      "reward": -3.0,
      "steps": 33
    },
    {
      "episode": 248,
      "reward": -3.0,
      "steps": 167
    },
    {
      "episode": 249,
      "reward": -3.0,
      "steps": 40
    },
    {
      "episode": 250,
      "reward": -3.0,
      "steps": 204
    },
    {
      "episode": 251,
      "reward": -3.0,
      "steps": 530
    },
    {
      "episode": 252,
      "reward": -3.0,
      "steps": 508
    },
    {
      "episode": 253,
      "reward": -3.0,
      "steps": 240
    },
    {
      "episode": 254,
      "reward": -3.0,
      "steps": 76
    },
    {
      "episode": 255,
      "reward": -3.0,
      "steps": 389
    },
    {
      "episode": 256,
      "reward": -3.0,
      "steps": 322
    },
    {
      "episode": 257,
      "reward": -3.0,
      "steps": 591
    },
    {
      "episode": 258,
      "reward": -3.0,
      "steps": 54
    },
    {
      "episode": 259,
      "reward": -3.0,
      "steps": 404
    },
    {
      "episode": 260,
      "reward": -3.0,
      "steps": 198
    },
    {
      "episode": 261,
      "reward": -3.0,
      "steps": 130
    },
    {
      "episode": 262,
      "reward": -3.0,
      "steps": 182
    },
    {
      "episode": 263,
      "reward": -3.0,
      "steps": 530
    },
    {
      "episode": 264,
      "reward": -3.0,
      "steps": 311
    },
    {
      "episode": 265,
      "reward": -3.0,
      "steps": 105
    },
    {
      "episode": 266,
      "reward": -3.0,
      "steps": 382
    },
    {
      "episode": 267,
      "reward": -3.0,
      "steps": 179
    },
    {
      "episode": 268,
      "reward": -3.0,
      "steps": 79
    },
    {
      "episode": 269,
      "reward": -3.0,
      "steps": 83
    },
    {
      "episode": 270,
      "reward": -3.0,
      "steps": 310
    },
    {
      "episode": 271,
      "reward": -3.0,
      "steps": 239
    },
    {
      "episode": 272,
      "reward": -3.0,
      "steps": 218
    },
    {
      "episode": 273,
      "reward": -3.0,
      "steps": 110
    },
    {
      "episode": 274,
      "reward": -3.0,
      "steps": 475
    },
    {
      "episode": 275,
      "reward": 0.0,
      "steps": 1000
    },
    {
      "episode": 276,
      "reward": -3.0,
      "steps": 227
    },
    {
      "episode": 277,
      "reward": -3.0,
      "steps": 307
    },
    {
      "episode": 278,
      "reward": -3.0,
      "steps": 420
    },
    {
      "episode": 279,
      "reward": -3.0,
      "steps": 108
    },
    {
      "episode": 280,
      "reward": -3.0,
      "steps": 818
    },
    {
      "episode": 281,
      "reward": -3.0,
      "steps": 901
    },
    {
      "episode": 282,
      "reward": -3.0,
      "steps": 102
    },
    {
      "episode": 283,
      "reward": -3.0,
      "steps": 111
    },
    {
      "episode": 284,
      "reward": -3.0,
      "steps": 86
    },
    {
      "episode": 285,
      "reward": -3.0,
      "steps": 206
    },
    {
      "episode": 286,
      "reward": -3.0,
      "steps": 259
    },
    {
      "episode": 287,
      "reward": -3.0,
      "steps": 579
    },
    {
      "episode": 288,
      "reward": -3.0,
      "steps": 129
    },
    {
      "episode": 289,
      "reward": -3.0,
      "steps": 409
    },
    {
      "episode": 290,
      "reward": -3.0,
      "steps": 672
    },
    {
      "episode": 291,
      "reward": -3.0,
      "steps": 207
    },
    {
      "episode": 292,
      "reward": -3.0,
      "steps": 187
    },
    {
      "episode": 293,
      "reward": -3.0,
      "steps": 565
    },
    {
      "episode": 294,
      "reward": -3.0,
      "steps": 441
    },
    {
      "episode": 295,
      "reward": -3.0,
      "steps": 201
    },
    {
      "episode": 296,
      "reward": -3.0,
      "steps": 157
    },
    {
      "episode": 297,
      "reward": -3.0,
      "steps": 125
    },
    {
      "episode": 298,
      "reward": -3.0,
      "steps": 410
    },
    {
      "episode": 299,
      "reward": -3.0,
      "steps": 369
    },
    {
      "episode": 300,
      "reward": -3.0,
      "steps": 284
    },
    {
      "episode": 301,
      "reward": -3.0,
      "steps": 199
    },
    {
      "episode": 302,
      "reward": -3.0,
      "steps": 134
    },
    {
      "episode": 303,
      "reward": -3.0,
      "steps": 341
    },
    {
      "episode": 304,
      "reward": -3.0,
      "steps": 124
    },
    {
      "episode": 305,
      "reward": -3.0,
      "steps": 305
    },
    {
      "episode": 306,
      "reward": 0.0,
      "steps": 1000
    },
    {
      "episode": 307,
      "reward": -3.0,
      "steps": 337
    },
    {
      "episode": 308,
      "reward": -3.0,
      "steps": 564
    },
    {
      "episode": 309,
      "reward": -3.0,
      "steps": 102
    },
    {
      "episode": 310,
      "reward": -3.0,
      "steps": 159
    },
    {
      "episode": 311,
      "reward": -3.0,
      "steps": 731
    },
    {
      "episode": 312,
      "reward": -3.0,
      "steps": 131
    },
    {
      "episode": 313,
      "reward": -3.0,
      "steps": 774
    },
    {
      "episode": 314,
      "reward": -3.0,
      "steps": 156
    },
    {
      "episode": 315,
      "reward": -3.0,
      "steps": 480
    },
    {
      "episode": 316,
      "reward": -3.0,
      "steps": 691
    },
    {
      "episode": 317,
      "reward": -3.0,
      "steps": 162
    },
    {
      "episode": 318,
      "reward": -3.0,
      "steps": 93
    },
    {
      "episode": 319,
      "reward": -3.0,
      "steps": 491
    },
    {
      "episode": 320,
      "reward": -3.0,
      "steps": 380
    },
    {
      "episode": 321,
      "reward": -3.0,
      "steps": 198
    },
    {
      "episode": 322,
      "reward": -3.0,
      "steps": 118
    },
    {
      "episode": 323,
      "reward": -3.0,
      "steps": 290
    },
    {
      "episode": 324,
      "reward": -3.0,
      "steps": 97
    },
    {
      "episode": 325,
      "reward": -3.0,
      "steps": 229
    },
    {
      "episode": 326,
      "reward": -3.0,
      "steps": 212
    },
    {
      "episode": 327,
      "reward": -3.0,
      "steps": 845
    },
    {
      "episode": 328,
      "reward": -3.0,
      "steps": 444
    },
    {
      "episode": 329,
      "reward": -3.0,
      "steps": 52
    },
    {
      "episode": 330,
      "reward": -3.0,
      "steps": 444
    },
    {
      "episode": 331,
      "reward": -3.0,
      "steps": 225
    },
    {
      "episode": 332,
      "reward": -3.0,
      "steps": 829
    },
    {
      "episode": 333,
      "reward": -3.0,
      "steps": 239
    },
    {
      "episode": 334,
      "reward": -3.0,
      "steps": 501
    },
    {
      "episode": 335,
      "reward": 0.0,
      "steps": 1000
    },
    {
      "episode": 336,
      "reward": -3.0,
      "steps": 720
    },
    {
      "episode": 337,
      "reward": -3.0,
      "steps": 177
    },
    {
      "episode": 338,
      "reward": -3.0,
      "steps": 137
    },
    {
      "episode": 339,
      "reward": -3.0,
      "steps": 380
    },
    {
      "episode": 340,
      "reward": -3.0,
      "steps": 18
    },
    {
      "episode": 341,
      "reward": -3.0,
      "steps": 310
    },
    {
      "episode": 342,
      "reward": -3.0,
      "steps": 406
    },
    {
      "episode": 343,
      "reward": -3.0,
      "steps": 479
    },
    {
      "episode": 344,
      "reward": -3.0,
      "steps": 96
    },
    {
      "episode": 345,
      "reward": -3.0,
      "steps": 136
    },
    {
      "episode": 346,
      "reward": -3.0,
      "steps": 385
    },
    {
      "episode": 347,
      "reward": -3.0,
      "steps": 802
    },
    {
      "episode": 348,
      "reward": -3.0,
      "steps": 275
    },
    {
      "episode": 349,
      "reward": -3.0,
      "steps": 126
    },
    {
      "episode": 350,
      "reward": -3.0,
      "steps": 431
    },
    {
      "episode": 351,
      "reward": -3.0,
      "steps": 256
    },
    {
      "episode": 352,
      "reward": -3.0,
      "steps": 348
    },
    {
      "episode": 353,
      "reward": -3.0,
      "steps": 471
    },
    {
      "episode": 354,
      "reward": 0.0,
      "steps": 1000
    },
    {
      "episode": 355,
      "reward": -3.0,
      "steps": 768
    },
    {
      "episode": 356,
      "reward": -3.0,
      "steps": 671
    },
    {
      "episode": 357,
      "reward": 1.0,
      "steps": 143
    },
    {
      "episode": 358,
      "reward": 1.0,
      "steps": 37
    },
    {
      "episode": 359,
      "reward": 1.0,
      "steps": 10
    },
    {
      "episode": 360,
      "reward": 1.0,
      "steps": 9
    },
    {
      "episode": 361,
      "reward": 1.0,
      "steps": 8
    },
    {
      "episode": 362,
      "reward": 1.0,
      "steps": 8
    },
    {
      "episode": 363,
      "reward": 1.0,
      "steps": 8
    },
    {
      "episode": 364,
      "reward": 1.0,
      "steps": 8
    },
    {
      "episode": 365,
      "reward": 1.0,
      "steps": 8
    },
    {
      "episode": 366,
      "reward": 1.0,
      "steps": 9
    },
    {
      "episode": 367,
      "reward": 1.0,
      "steps": 8
    },
    {
      "episode": 368,
      "reward": 1.0,
      "steps": 8
    },
    {
      "episode": 369,
      "reward": 1.0,
      "steps": 9
    },
    {
      "episode": 370,
      "reward": 1.0,
      "steps": 12
    },
    {
      "episode": 371,
      "reward": 1.0,
      "steps": 8
    },
    {
      "episode": 372,
      "reward": 1.0,
      "steps": 10
    },
    {
      "episode": 373,
      "reward": 1.0,
      "steps": 8
    },
    {
      "episode": 374,
      "reward": 1.0,
      "steps": 9
    },
    {
      "episode": 375,
      "reward": 1.0,
      "steps": 8
    },
    {
      "episode": 376,
      "reward": 1.0,
      "steps": 10
    },
    {
      "episode": 377,
      "reward": 1.0,
      "steps": 12
    },
    {
      "episode": 378,
      "reward": 1.0,
      "steps": 8
    },
    {
      "episode": 379,
      "reward": 1.0,
      "steps": 10
    },
    {
      "episode": 380,
      "reward": 1.0,
      "steps": 8
    },
    {
      "episode": 381,
      "reward": 1.0,
      "steps": 9
    },
    {
      "episode": 382,
      "reward": 1.0,
      "steps": 8
    },
    {
      "episode": 383,
      "reward": 1.0,
      "steps": 10
    },
    {
      "episode": 384,
      "reward": 1.0,
      "steps": 8
    },
    {
      "episode": 385,
      "reward": 1.0,
      "steps": 8
    },
    {
      "episode": 386,
      "reward": 1.0,
      "steps": 9
    },
    {
      "episode": 387,
      "reward": 1.0,
      "steps": 8
    },
    {
      "episode": 388,
      "reward": 1.0,
      "steps": 10
    },
    {
      "episode": 389,
      "reward": 1.0,
      "steps": 10
    },
    {
      "episode": 390,
      "reward": 1.0,
      "steps": 8
    },
    {
      "episode": 391,
      "reward": 1.0,
      "steps": 9
    },
    {
      "episode": 392,
      "reward": 1.0,
      "steps": 8
    },
    {
      "episode": 393,
      "reward": 1.0,
      "steps": 8
    },
    {
      "episode": 394,
      "reward": 1.0,
      "steps": 12
    },
    {
      "episode": 395,
      "reward": 1.0,
      "steps": 10
    },
    {
      "episode": 396,
      "reward": 1.0,
      "steps": 10
    },
    {
      "episode": 397,
      "reward": 1.0,
      "steps": 8
    },
    {
      "episode": 398,
      "reward": 1.0,
      "steps": 12
    },
    {
      "episode": 399,
      "reward": 1.0,
      "steps": 8
    },
    {
      "episode": 400,
      "reward": 1.0,
      "steps": 8
    },
    {
      "episode": 401,
      "reward": 1.0,
      "steps": 12
    },
    {
      "episode": 402,
      "reward": 1.0,
      "steps": 8
    },
    {
      "episode": 403,
      "reward": 1.0,
      "steps": 8
    },
    {
      "episode": 404,
      "reward": 1.0,
      "steps": 8
    },
    {
      "episode": 405,
      "reward": 1.0,
      "steps": 8
    },
    {
      "episode": 406,
      "reward": 1.0,
      "steps": 10
    },
    {
      "episode": 407,
      "reward": 1.0,
      "steps": 8
    },
    {
      "episode": 408,
      "reward": 1.0,
      "steps": 8
    },
    {
      "episode": 409,
      "reward": 1.0,
      "steps": 10
    },
    {
      "episode": 410,
      "reward": 1.0,
      "steps": 8
    },
    {
      "episode": 411,
      "reward": 1.0,
      "steps": 8
    },
    {
      "episode": 412,
      "reward": 1.0,
      "steps": 8
    },
    {
      "episode": 413,
      "reward": 1.0,
      "steps": 10
    },
    {
      "episode": 414,
      "reward": 1.0,
      "steps": 12
    },
    {
      "episode": 415,
      "reward": 1.0,
      "steps": 8
    },
    {
      "episode": 416,
      "reward": 1.0,
      "steps": 10
    },
    {
      "episode": 417,
      "reward": 1.0,
      "steps": 10
    },
    {
      "episode": 418,
      "reward": 1.0,
      "steps": 8
    },
    {
      "episode": 419,
      "reward": 1.0,
      "steps": 10
    },
    {
      "episode": 420,
      "reward": 1.0,
      "steps": 8
    },
    {
      "episode": 421,
      "reward": 1.0,
      "steps": 8
    },
    {
      "episode": 422,
      "reward": 1.0,
      "steps": 10
    },
    {
      "episode": 423,
      "reward": 1.0,
      "steps": 8
    },
    {
      "episode": 424,
      "reward": 1.0,
      "steps": 10
    },
    {
      "episode": 425,
      "reward": 1.0,
      "steps": 8
    },
    {
      "episode": 426,
      "reward": 1.0,
      "steps": 8
    },
    {
      "episode": 427,
      "reward": 1.0,
      "steps": 10
    },
    {
      "episode": 428,
      "reward": 1.0,
      "steps": 8
    },
    {
      "episode": 429,
      "reward": 1.0,
      "steps": 8
    },
    {
      "episode": 430,
      "reward": 1.0,
      "steps": 10
    },
    {
      "episode": 431,
      "reward": 1.0,
      "steps": 10
    },
    {
      "episode": 432,
      "reward": 1.0,
      "steps": 8
    },
    {
      "episode": 433,
      "reward": 1.0,
      "steps": 8
    },
    {
      "episode": 434,
      "reward": 1.0,
      "steps": 8
    },
    {
      "episode": 435,
      "reward": 1.0,
      "steps": 10
    },
    {
      "episode": 436,
      "reward": 1.0,
      "steps": 8
    },
    {
      "episode": 437,
      "reward": 1.0,
      "steps": 10
    },
    {
      "episode": 438,
      "reward": 1.0,
      "steps": 8
    },
    {
      "episode": 439,
      "reward": 1.0,
      "steps": 8
    },
    {
      "episode": 440,
      "reward": 1.0,
      "steps": 9
    },
    {
      "episode": 441,
      "reward": 1.0,
      "steps": 12
    },
    {
      "episode": 442,
      "reward": 1.0,
      "steps": 10
    },
    {
      "episode": 443,
      "reward": 1.0,
      "steps": 10
    },
    {
      "episode": 444,
      "reward": 1.0,
      "steps": 12
    },
    {
      "episode": 445,
      "reward": 1.0,
      "steps": 8
    },
    {
      "episode": 446,
      "reward": 1.0,
      "steps": 11
    },
    {
      "episode": 447,
      "reward": 1.0,
      "steps": 8
    },
    {
      "episode": 448,
      "reward": 1.0,
      "steps": 8
    },
    {
      "episode": 449,
      "reward": 1.0,
      "steps": 8
    },
    {
      "episode": 450,
      "reward": 1.0,
      "steps": 10
    },
    {
      "episode": 451,
      "reward": 1.0,
      "steps": 12
    },
    {
      "episode": 452,
      "reward": 1.0,
      "steps": 8
    },
    {
      "episode": 453,
      "reward": 1.0,
      "steps": 10
    },
    {
      "episode": 454,
      "reward": 1.0,
      "steps": 8
    },
    {
      "episode": 455,
      "reward": 1.0,
      "steps": 8
    },
    {
      "episode": 456,
      "reward": 1.0,
      "steps": 10
    },
    {
      "episode": 457,
      "reward": 1.0,
      "steps": 10
    },
    {
      "episode": 458,
      "reward": 1.0,
      "steps": 8
    },
    {
      "episode": 459,
      "reward": 1.0,
      "steps": 10
    },
    {
      "episode": 460,
      "reward": 1.0,
      "steps": 8
    },
    {
      "episode": 461,
      "reward": 1.0,
      "steps": 10
    },
    {
      "episode": 462,
      "reward": 1.0,
      "steps": 10
    },
    {
      "episode": 463,
      "reward": 1.0,
      "steps": 10
    },
    {
      "episode": 464,
      "reward": 1.0,
      "steps": 8
    },
    {
      "episode": 465,
      "reward": 1.0,
      "steps": 8
    },
    {
      "episode": 466,
      "reward": 1.0,
      "steps": 8
    },
    {
      "episode": 467,
      "reward": 1.0,
      "steps": 10
    },
    {
      "episode": 468,
      "reward": 1.0,
      "steps": 8
    },
    {
      "episode": 469,
      "reward": 1.0,
      "steps": 8
    },
    {
      "episode": 470,
      "reward": 1.0,
      "steps": 8
    },
    {
      "episode": 471,
      "reward": 1.0,
      "steps": 8
    },
    {
      "episode": 472,
      "reward": 1.0,
      "steps": 12
    },
    {
      "episode": 473,
      "reward": 1.0,
      "steps": 8
    },
    {
      "episode": 474,
      "reward": 1.0,
      "steps": 13
    },
    {
      "episode": 475,
      "reward": 1.0,
      "steps": 8
    },
    {
      "episode": 476,
      "reward": 1.0,
      "steps": 8
    },
    {
      "episode": 477,
      "reward": 1.0,
      "steps": 10
    },
    {
      "episode": 478,
      "reward": 1.0,
      "steps": 8
    },
    {
      "episode": 479,
      "reward": 1.0,
      "steps": 10
    },
    {
      "episode": 480,
      "reward": 1.0,
      "steps": 9
    },
    {
      "episode": 481,
      "reward": 1.0,
      "steps": 9
    },
    {
      "episode": 482,
      "reward": 1.0,
      "steps": 8
    },
    {
      "episode": 483,
      "reward": 1.0,
      "steps": 10
    },
    {
      "episode": 484,
      "reward": 1.0,
      "steps": 8
    },
    {
      "episode": 485,
      "reward": 1.0,
      "steps": 8
    },
    {
      "episode": 486,
      "reward": 1.0,
      "steps": 8
    },
    {
      "episode": 487,
      "reward": 1.0,
      "steps": 8
    },
    {
      "episode": 488,
      "reward": 1.0,
      "steps": 8
    },
    {
      "episode": 489,
      "reward": 1.0,
      "steps": 8
    },
    {
      "episode": 490,
      "reward": 1.0,
      "steps": 8
    },
    {
      "episode": 491,
      "reward": 1.0,
      "steps": 8
    },
    {
      "episode": 492,
      "reward": 1.0,
      "steps": 8
    },
    {
      "episode": 493,
      "reward": 1.0,
      "steps": 8
    },
    {
      "episode": 494,
      "reward": 1.0,
      "steps": 8
    },
    {
      "episode": 495,
      "reward": 1.0,
      "steps": 8
    },
    {
      "episode": 496,
      "reward": 1.0,
      "steps": 8
    },
    {
      "episode": 497,
      "reward": 1.0,
      "steps": 8
    },
    {
      "episode": 498,
      "reward": 1.0,
      "steps": 8
    },
    {
      "episode": 499,
      "reward": 1.0,
      "steps": 8
    },
    {
      "episode": 500,
      "reward": 1.0,
      "steps": 10
    },
    {
      "episode": 501,
      "reward": 1.0,
      "steps": 12
    },
    {
      "episode": 502,
      "reward": 1.0,
      "steps": 9
    },
    {
      "episode": 503,
      "reward": 1.0,
      "steps": 8
    },
    {
      "episode": 504,
      "reward": 1.0,
      "steps": 8
    },
    {
      "episode": 505,
      "reward": 1.0,
      "steps": 8
    },
    {
      "episode": 506,
      "reward": 1.0,
      "steps": 10
    },
    {
      "episode": 507,
      "reward": 1.0,
      "steps": 8
    },
    {
      "episode": 508,
      "reward": 1.0,
      "steps": 8
    },
    {
      "episode": 509,
      "reward": 1.0,
      "steps": 8
    },
    {
      "episode": 510,
      "reward": 1.0,
      "steps": 8
    },
    {
      "episode": 511,
      "reward": 1.0,
      "steps": 10
    },
    {
      "episode": 512,
      "reward": 1.0,
      "steps": 8
    },
    {
      "episode": 513,
      "reward": 1.0,
      "steps": 8
    },
    {
      "episode": 514,
      "reward": 1.0,
      "steps": 8
    },
    {
      "episode": 515,
      "reward": 1.0,
      "steps": 8
    },
    {
      "episode": 516,
      "reward": 1.0,
      "steps": 8
    },
    {
      "episode": 517,
      "reward": 1.0,
      "steps": 12
    },
    {
      "episode": 518,
      "reward": 1.0,
      "steps": 8
    },
    {
      "episode": 519,
      "reward": 1.0,
      "steps": 8
    },
    {
      "episode": 520,
      "reward": 1.0,
      "steps": 8
    },
    {
      "episode": 521,
      "reward": 1.0,
      "steps": 8
    },
    {
      "episode": 522,
      "reward": 1.0,
      "steps": 8
    },
    {
      "episode": 523,
      "reward": 1.0,
      "steps": 8
    },
    {
      "episode": 524,
      "reward": 1.0,
      "steps": 8
    },
    {
      "episode": 525,
      "reward": 1.0,
      "steps": 8
    },
    {
      "episode": 526,
      "reward": 1.0,
      "steps": 8
    },
    {
      "episode": 527,
      "reward": 1.0,
      "steps": 8
    },
    {
      "episode": 528,
      "reward": 1.0,
      "steps": 8
    },
    {
      "episode": 529,
      "reward": 1.0,
      "steps": 10
    },
    {
      "episode": 530,
      "reward": 1.0,
      "steps": 8
    },
    {
      "episode": 531,
      "reward": 1.0,
      "steps": 8
    },
    {
      "episode": 532,
      "reward": 1.0,
      "steps": 8
    },
    {
      "episode": 533,
      "reward": 1.0,
      "steps": 8
    },
    {
      "episode": 534,
      "reward": 1.0,
      "steps": 8
    },
    {
      "episode": 535,
      "reward": 1.0,
      "steps": 8
    },
    {
      "episode": 536,
      "reward": 1.0,
      "steps": 8
    },
    {
      "episode": 537,
      "reward": 1.0,
      "steps": 8
    },
    {
      "episode": 538,
      "reward": 1.0,
      "steps": 8
    },
    {
      "episode": 539,
      "reward": 1.0,
      "steps": 8
    },
    {
      "episode": 540,
      "reward": 1.0,
      "steps": 8
    },
    {
      "episode": 541,
      "reward": 1.0,
      "steps": 13
    },
    {
      "episode": 542,
      "reward": 1.0,
      "steps": 10
    },
    {
      "episode": 543,
      "reward": 1.0,
      "steps": 10
    },
    {
      "episode": 544,
      "reward": 1.0,
      "steps": 8
    },
    {
      "episode": 545,
      "reward": 1.0,
      "steps": 8
    },
    {
      "episode": 546,
      "reward": 1.0,
      "steps": 10
    },
    {
      "episode": 547,
      "reward": 1.0,
      "steps": 8
    },
    {
      "episode": 548,
      "reward": 1.0,
      "steps": 9
    },
    {
      "episode": 549,
      "reward": 1.0,
      "steps": 8
    },
    {
      "episode": 550,
      "reward": 1.0,
      "steps": 8
    },
    {
      "episode": 551,
      "reward": 1.0,
      "steps": 8
    },
    {
      "episode": 552,
      "reward": 1.0,
      "steps": 8
    },
    {
      "episode": 553,
      "reward": 1.0,
      "steps": 11
    },
    {
      "episode": 554,
      "reward": 1.0,
      "steps": 8
    },
    {
      "episode": 555,
      "reward": 1.0,
      "steps": 8
    },
    {
      "episode": 556,
      "reward": 1.0,
      "steps": 10
    },
    {
      "episode": 557,
      "reward": 1.0,
      "steps": 8
    },
    {
      "episode": 558,
      "reward": 1.0,
      "steps": 8
    },
    {
      "episode": 559,
      "reward": 1.0,
      "steps": 8
    },
    {
      "episode": 560,
      "reward": 1.0,
      "steps": 8
    },
    {
      "episode": 561,
      "reward": 1.0,
      "steps": 9
    },
    {
      "episode": 562,
      "reward": 1.0,
      "steps": 8
    },
    {
      "episode": 563,
      "reward": 1.0,
      "steps": 12
    },
    {
      "episode": 564,
      "reward": 1.0,
      "steps": 8
    },
    {
      "episode": 565,
      "reward": 1.0,
      "steps": 8
    },
    {
      "episode": 566,
      "reward": 1.0,
      "steps": 8
    },
    {
      "episode": 567,
      "reward": 1.0,
      "steps": 11
    },
    {
      "episode": 568,
      "reward": 1.0,
      "steps": 8
    },
    {
      "episode": 569,
      "reward": 1.0,
      "steps": 8
    },
    {
      "episode": 570,
      "reward": 1.0,
      "steps": 8
    },
    {
      "episode": 571,
      "reward": 1.0,
      "steps": 8
    },
    {
      "episode": 572,
      "reward": 1.0,
      "steps": 9
    },
    {
      "episode": 573,
      "reward": 1.0,
      "steps": 10
    },
    {
      "episode": 574,
      "reward": 1.0,
      "steps": 8
    },
    {
      "episode": 575,
      "reward": 1.0,
      "steps": 8
    },
    {
      "episode": 576,
      "reward": 1.0,
      "steps": 8
    },
    {
      "episode": 577,
      "reward": 1.0,
      "steps": 8
    },
    {
      "episode": 578,
      "reward": 1.0,
      "steps": 8
    },
    {
      "episode": 579,
      "reward": 1.0,
      "steps": 8
    },
    {
      "episode": 580,
      "reward": 1.0,
      "steps": 8
    },
    {
      "episode": 581,
      "reward": 1.0,
      "steps": 10
    },
    {
      "episode": 582,
      "reward": 1.0,
      "steps": 8
    },
    {
      "episode": 583,
      "reward": 1.0,
      "steps": 8
    },
    {
      "episode": 584,
      "reward": 1.0,
      "steps": 8
    },
    {
      "episode": 585,
      "reward": 1.0,
      "steps": 8
    },
    {
      "episode": 586,
      "reward": 1.0,
      "steps": 8
    },
    {
      "episode": 587,
      "reward": 1.0,
      "steps": 8
    },
    {
      "episode": 588,
      "reward": 1.0,
      "steps": 8
    },
    {
      "episode": 589,
      "reward": 1.0,
      "steps": 8
    },
    {
      "episode": 590,
      "reward": 1.0,
      "steps": 8
    },
    {
      "episode": 591,
      "reward": 1.0,
      "steps": 8
    },
    {
      "episode": 592,
      "reward": 1.0,
      "steps": 8
    },
    {
      "episode": 593,
      "reward": 1.0,
      "steps": 8
    },
    {
      "episode": 594,
      "reward": 1.0,
      "steps": 8
    },
    {
      "episode": 595,
      "reward": 1.0,
      "steps": 8
    },
    {
      "episode": 596,
      "reward": 1.0,
      "steps": 12
    },
    {
      "episode": 597,
      "reward": 1.0,
      "steps": 10
    },
    {
      "episode": 598,
      "reward": 1.0,
      "steps": 8
    },
    {
      "episode": 599,
      "reward": 1.0,
      "steps": 12
    },
    {
      "episode": 600,
      "reward": 1.0,
      "steps": 8
    },
    {
      "episode": 601,
      "reward": 1.0,
      "steps": 8
    },
    {
      "episode": 602,
      "reward": 1.0,
      "steps": 8
    },
    {
      "episode": 603,
      "reward": 1.0,
      "steps": 8
    },
    {
      "episode": 604,
      "reward": 1.0,
      "steps": 9
    },
    {
      "episode": 605,
      "reward": 1.0,
      "steps": 8
    },
    {
      "episode": 606,
      "reward": 1.0,
      "steps": 10
    },
    {
      "episode": 607,
      "reward": 1.0,
      "steps": 8
    },
    {
      "episode": 608,
      "reward": 1.0,
      "steps": 8
    },
    {
      "episode": 609,
      "reward": 1.0,
      "steps": 10
    },
    {
      "episode": 610,
      "reward": 1.0,
      "steps": 8
    },
    {
      "episode": 611,
      "reward": 1.0,
      "steps": 8
    },
    {
      "episode": 612,
      "reward": 1.0,
      "steps": 8
    },
    {
      "episode": 613,
      "reward": 1.0,
      "steps": 10
    },
    {
      "episode": 614,
      "reward": 1.0,
      "steps": 10
    },
    {
      "episode": 615,
      "reward": 1.0,
      "steps": 8
    },
    {
      "episode": 616,
      "reward": 1.0,
      "steps": 8
    },
    {
      "episode": 617,
      "reward": 1.0,
      "steps": 8
    },
    {
      "episode": 618,
      "reward": 1.0,
      "steps": 8
    },
    {
      "episode": 619,
      "reward": 1.0,
      "steps": 10
    },
    {
      "episode": 620,
      "reward": 1.0,
      "steps": 9
    },
    {
      "episode": 621,
      "reward": 1.0,
      "steps": 10
    },
    {
      "episode": 622,
      "reward": 1.0,
      "steps": 8
    },
    {
      "episode": 623,
      "reward": 1.0,
      "steps": 8
    },
    {
      "episode": 624,
      "reward": 1.0,
      "steps": 8
    },
    {
      "episode": 625,
      "reward": 1.0,
      "steps": 8
    },
    {
      "episode": 626,
      "reward": 1.0,
      "steps": 8
    },
    {
      "episode": 627,
      "reward": 1.0,
      "steps": 8
    },
    {
      "episode": 628,
      "reward": 1.0,
      "steps": 9
    },
    {
      "episode": 629,
      "reward": 1.0,
      "steps": 12
    },
    {
      "episode": 630,
      "reward": 1.0,
      "steps": 8
    },
    {
      "episode": 631,
      "reward": 1.0,
      "steps": 8
    },
    {
      "episode": 632,
      "reward": 1.0,
      "steps": 8
    },
    {
      "episode": 633,
      "reward": 1.0,
      "steps": 8
    },
    {
      "episode": 634,
      "reward": 1.0,
      "steps": 8
    },
    {
      "episode": 635,
      "reward": 1.0,
      "steps": 8
    },
    {
      "episode": 636,
      "reward": 1.0,
      "steps": 9
    },
    {
      "episode": 637,
      "reward": 1.0,
      "steps": 8
    },
    {
      "episode": 638,
      "reward": 1.0,
      "steps": 10
    },
    {
      "episode": 639,
      "reward": 1.0,
      "steps": 8
    },
    {
      "episode": 640,
      "reward": 1.0,
      "steps": 10
    },
    {
      "episode": 641,
      "reward": 1.0,
      "steps": 8
    },
    {
      "episode": 642,
      "reward": 1.0,
      "steps": 9
    },
    {
      "episode": 643,
      "reward": 1.0,
      "steps": 8
    },
    {
      "episode": 644,
      "reward": 1.0,
      "steps": 10
    },
    {
      "episode": 645,
      "reward": 1.0,
      "steps": 8
    },
    {
      "episode": 646,
      "reward": 1.0,
      "steps": 8
    },
    {
      "episode": 647,
      "reward": 1.0,
      "steps": 8
    },
    {
      "episode": 648,
      "reward": 1.0,
      "steps": 9
    },
    {
      "episode": 649,
      "reward": 1.0,
      "steps": 10
    },
    {
      "episode": 650,
      "reward": 1.0,
      "steps": 8
    },
    {
      "episode": 651,
      "reward": 1.0,
      "steps": 8
    },
    {
      "episode": 652,
      "reward": 1.0,
      "steps": 8
    },
    {
      "episode": 653,
      "reward": 1.0,
      "steps": 8
    },
    {
      "episode": 654,
      "reward": 1.0,
      "steps": 8
    },
    {
      "episode": 655,
      "reward": 1.0,
      "steps": 8
    },
    {
      "episode": 656,
      "reward": 1.0,
      "steps": 8
    },
    {
      "episode": 657,
      "reward": 1.0,
      "steps": 8
    },
    {
      "episode": 658,
      "reward": 1.0,
      "steps": 8
    },
    {
      "episode": 659,
      "reward": 1.0,
      "steps": 8
    },
    {
      "episode": 660,
      "reward": 1.0,
      "steps": 8
    },
    {
      "episode": 661,
      "reward": 1.0,
      "steps": 8
    },
    {
      "episode": 662,
      "reward": 1.0,
      "steps": 8
    },
    {
      "episode": 663,
      "reward": 1.0,
      "steps": 8
    },
    {
      "episode": 664,
      "reward": 1.0,
      "steps": 8
    },
    {
      "episode": 665,
      "reward": 1.0,
      "steps": 8
    },
    {
      "episode": 666,
      "reward": 1.0,
      "steps": 8
    },
    {
      "episode": 667,
      "reward": 1.0,
      "steps": 9
    },
    {
      "episode": 668,
      "reward": 1.0,
      "steps": 8
    },
    {
      "episode": 669,
      "reward": 1.0,
      "steps": 8
    },
    {
      "episode": 670,
      "reward": 1.0,
      "steps": 8
    },
    {
      "episode": 671,
      "reward": 1.0,
      "steps": 8
    },
    {
      "episode": 672,
      "reward": 1.0,
      "steps": 8
    },
    {
      "episode": 673,
      "reward": 1.0,
      "steps": 8
    },
    {
      "episode": 674,
      "reward": 1.0,
      "steps": 11
    },
    {
      "episode": 675,
      "reward": 1.0,
      "steps": 12
    },
    {
      "episode": 676,
      "reward": 1.0,
      "steps": 8
    },
    {
      "episode": 677,
      "reward": 1.0,
      "steps": 10
    },
    {
      "episode": 678,
      "reward": 1.0,
      "steps": 8
    },
    {
      "episode": 679,
      "reward": 1.0,
      "steps": 8
    },
    {
      "episode": 680,
      "reward": 1.0,
      "steps": 10
    },
    {
      "episode": 681,
      "reward": 1.0,
      "steps": 8
    },
    {
      "episode": 682,
      "reward": 1.0,
      "steps": 8
    },
    {
      "episode": 683,
      "reward": 1.0,
      "steps": 8
    },
    {
      "episode": 684,
      "reward": 1.0,
      "steps": 8
    },
    {
      "episode": 685,
      "reward": 1.0,
      "steps": 8
    },
    {
      "episode": 686,
      "reward": 1.0,
      "steps": 8
    },
    {
      "episode": 687,
      "reward": 1.0,
      "steps": 10
    },
    {
      "episode": 688,
      "reward": 1.0,
      "steps": 8
    },
    {
      "episode": 689,
      "reward": 1.0,
      "steps": 8
    },
    {
      "episode": 690,
      "reward": 1.0,
      "steps": 8
    },
    {
      "episode": 691,
      "reward": 1.0,
      "steps": 8
    },
    {
      "episode": 692,
      "reward": 1.0,
      "steps": 8
    },
    {
      "episode": 693,
      "reward": 1.0,
      "steps": 9
    },
    {
      "episode": 694,
      "reward": 1.0,
      "steps": 8
    },
    {
      "episode": 695,
      "reward": 1.0,
      "steps": 8
    },
    {
      "episode": 696,
      "reward": 1.0,
      "steps": 8
    },
    {
      "episode": 697,
      "reward": 1.0,
      "steps": 8
    },
    {
      "episode": 698,
      "reward": 1.0,
      "steps": 8
    },
    {
      "episode": 699,
      "reward": 1.0,
      "steps": 8
    },
    {
      "episode": 700,
      "reward": 1.0,
      "steps": 8
    },
    {
      "episode": 701,
      "reward": 1.0,
      "steps": 8
    },
    {
      "episode": 702,
      "reward": 1.0,
      "steps": 8
    },
    {
      "episode": 703,
      "reward": 1.0,
      "steps": 10
    },
    {
      "episode": 704,
      "reward": 1.0,
      "steps": 8
    },
    {
      "episode": 705,
      "reward": 1.0,
      "steps": 8
    },
    {
      "episode": 706,
      "reward": 1.0,
      "steps": 10
    },
    {
      "episode": 707,
      "reward": 1.0,
      "steps": 8
    },
    {
      "episode": 708,
      "reward": 1.0,
      "steps": 8
    },
    {
      "episode": 709,
      "reward": 1.0,
      "steps": 10
    },
    {
      "episode": 710,
      "reward": 1.0,
      "steps": 8
    },
    {
      "episode": 711,
      "reward": 1.0,
      "steps": 10
    },
    {
      "episode": 712,
      "reward": 1.0,
      "steps": 8
    },
    {
      "episode": 713,
      "reward": 1.0,
      "steps": 8
    },
    {
      "episode": 714,
      "reward": 1.0,
      "steps": 12
    },
    {
      "episode": 715,
      "reward": 1.0,
      "steps": 10
    },
    {
      "episode": 716,
      "reward": 1.0,
      "steps": 8
    },
    {
      "episode": 717,
      "reward": 1.0,
      "steps": 8
    },
    {
      "episode": 718,
      "reward": 1.0,
      "steps": 8
    },
    {
      "episode": 719,
      "reward": 1.0,
      "steps": 8
    },
    {
      "episode": 720,
      "reward": 1.0,
      "steps": 8
    },
    {
      "episode": 721,
      "reward": 1.0,
      "steps": 10
    },
    {
      "episode": 722,
      "reward": 1.0,
      "steps": 8
    },
    {
      "episode": 723,
      "reward": 1.0,
      "steps": 8
    },
    {
      "episode": 724,
      "reward": 1.0,
      "steps": 8
    },
    {
      "episode": 725,
      "reward": 1.0,
      "steps": 8
    },
    {
      "episode": 726,
      "reward": 1.0,
      "steps": 8
    },
    {
      "episode": 727,
      "reward": 1.0,
      "steps": 8
    },
    {
      "episode": 728,
      "reward": 1.0,
      "steps": 8
    },
    {
      "episode": 729,
      "reward": 1.0,
      "steps": 12
    },
    {
      "episode": 730,
      "reward": 1.0,
      "steps": 8
    },
    {
      "episode": 731,
      "reward": 1.0,
      "steps": 8
    },
    {
      "episode": 732,
      "reward": 1.0,
      "steps": 10
    },
    {
      "episode": 733,
      "reward": 1.0,
      "steps": 10
    },
    {
      "episode": 734,
      "reward": 1.0,
      "steps": 8
    },
    {
      "episode": 735,
      "reward": 1.0,
      "steps": 8
    },
    {
      "episode": 736,
      "reward": 1.0,
      "steps": 8
    },
    {
      "episode": 737,
      "reward": 1.0,
      "steps": 8
    },
    {
      "episode": 738,
      "reward": 1.0,
      "steps": 8
    },
    {
      "episode": 739,
      "reward": 1.0,
      "steps": 8
    },
    {
      "episode": 740,
      "reward": 1.0,
      "steps": 8
    },
    {
      "episode": 741,
      "reward": 1.0,
      "steps": 8
    },
    {
      "episode": 742,
      "reward": 1.0,
      "steps": 8
    },
    {
      "episode": 743,
      "reward": 1.0,
      "steps": 8
    },
    {
      "episode": 744,
      "reward": 1.0,
      "steps": 8
    },
    {
      "episode": 745,
      "reward": 1.0,
      "steps": 8
    },
    {
      "episode": 746,
      "reward": 1.0,
      "steps": 8
    },
    {
      "episode": 747,
      "reward": 1.0,
      "steps": 8
    },
    {
      "episode": 748,
      "reward": 1.0,
      "steps": 8
    },
    {
      "episode": 749,
      "reward": 1.0,
      "steps": 8
    },
    {
      "episode": 750,
      "reward": 1.0,
      "steps": 8
    },
    {
      "episode": 751,
      "reward": 1.0,
      "steps": 8
    },
    {
      "episode": 752,
      "reward": 1.0,
      "steps": 8
    },
    {
      "episode": 753,
      "reward": 1.0,
      "steps": 8
    },
    {
      "episode": 754,
      "reward": 1.0,
      "steps": 8
    },
    {
      "episode": 755,
      "reward": 1.0,
      "steps": 8
    },
    {
      "episode": 756,
      "reward": 1.0,
      "steps": 8
    },
    {
      "episode": 757,
      "reward": 1.0,
      "steps": 8
    },
    {
      "episode": 758,
      "reward": 1.0,
      "steps": 8
    },
    {
      "episode": 759,
      "reward": 1.0,
      "steps": 8
    },
    {
      "episode": 760,
      "reward": 1.0,
      "steps": 8
    },
    {
      "episode": 761,
      "reward": 1.0,
      "steps": 8
    },
    {
      "episode": 762,
      "reward": 1.0,
      "steps": 10
    },
    {
      "episode": 763,
      "reward": 1.0,
      "steps": 8
    },
    {
      "episode": 764,
      "reward": 1.0,
      "steps": 8
    },
    {
      "episode": 765,
      "reward": 1.0,
      "steps": 8
    },
    {
      "episode": 766,
      "reward": 1.0,
      "steps": 8
    },
    {
      "episode": 767,
      "reward": 1.0,
      "steps": 10
    },
    {
      "episode": 768,
      "reward": 1.0,
      "steps": 8
    },
    {
      "episode": 769,
      "reward": 1.0,
      "steps": 9
    },
    {
      "episode": 770,
      "reward": 1.0,
      "steps": 8
    },
    {
      "episode": 771,
      "reward": 1.0,
      "steps": 8
    },
    {
      "episode": 772,
      "reward": 1.0,
      "steps": 8
    },
    {
      "episode": 773,
      "reward": 1.0,
      "steps": 8
    },
    {
      "episode": 774,
      "reward": 1.0,
      "steps": 8
    },
    {
      "episode": 775,
      "reward": 1.0,
      "steps": 8
    },
    {
      "episode": 776,
      "reward": 1.0,
      "steps": 8
    },
    {
      "episode": 777,
      "reward": 1.0,
      "steps": 8
    },
    {
      "episode": 778,
      "reward": 1.0,
      "steps": 8
    },
    {
      "episode": 779,
      "reward": 1.0,
      "steps": 8
    },
    {
      "episode": 780,
      "reward": 1.0,
      "steps": 10
    },
    {
      "episode": 781,
      "reward": 1.0,
      "steps": 8
    },
    {
      "episode": 782,
      "reward": 1.0,
      "steps": 8
    },
    {
      "episode": 783,
      "reward": 1.0,
      "steps": 8
    },
    {
      "episode": 784,
      "reward": 1.0,
      "steps": 9
    },
    {
      "episode": 785,
      "reward": 1.0,
      "steps": 9
    },
    {
      "episode": 786,
      "reward": 1.0,
      "steps": 8
    },
    {
      "episode": 787,
      "reward": 1.0,
      "steps": 8
    },
    {
      "episode": 788,
      "reward": 1.0,
      "steps": 8
    },
    {
      "episode": 789,
      "reward": 1.0,
      "steps": 8
    },
    {
      "episode": 790,
      "reward": 1.0,
      "steps": 10
    },
    {
      "episode": 791,
      "reward": 1.0,
      "steps": 9
    },
    {
      "episode": 792,
      "reward": 1.0,
      "steps": 8
    },
    {
      "episode": 793,
      "reward": 1.0,
      "steps": 8
    },
    {
      "episode": 794,
      "reward": 1.0,
      "steps": 8
    },
    {
      "episode": 795,
      "reward": 1.0,
      "steps": 8
    },
    {
      "episode": 796,
      "reward": 1.0,
      "steps": 8
    },
    {
      "episode": 797,
      "reward": 1.0,
      "steps": 8
    },
    {
      "episode": 798,
      "reward": 1.0,
      "steps": 8
    },
    {
      "episode": 799,
      "reward": 1.0,
      "steps": 8
    },
    {
      "episode": 800,
      "reward": 1.0,
      "steps": 8
    },
    {
      "episode": 801,
      "reward": 1.0,
      "steps": 8
    },
    {
      "episode": 802,
      "reward": 1.0,
      "steps": 8
    },
    {
      "episode": 803,
      "reward": 1.0,
      "steps": 8
    },
    {
      "episode": 804,
      "reward": 1.0,
      "steps": 8
    },
    {
      "episode": 805,
      "reward": 1.0,
      "steps": 10
    },
    {
      "episode": 806,
      "reward": 1.0,
      "steps": 10
    },
    {
      "episode": 807,
      "reward": 1.0,
      "steps": 8
    },
    {
      "episode": 808,
      "reward": 1.0,
      "steps": 8
    },
    {
      "episode": 809,
      "reward": 1.0,
      "steps": 10
    },
    {
      "episode": 810,
      "reward": 1.0,
      "steps": 8
    },
    {
      "episode": 811,
      "reward": 1.0,
      "steps": 8
    },
    {
      "episode": 812,
      "reward": 1.0,
      "steps": 8
    },
    {
      "episode": 813,
      "reward": 1.0,
      "steps": 8
    },
    {
      "episode": 814,
      "reward": 1.0,
      "steps": 8
    },
    {
      "episode": 815,
      "reward": 1.0,
      "steps": 8
    },
    {
      "episode": 816,
      "reward": 1.0,
      "steps": 10
    },
    {
      "episode": 817,
      "reward": 1.0,
      "steps": 8
    },
    {
      "episode": 818,
      "reward": 1.0,
      "steps": 8
    },
    {
      "episode": 819,
      "reward": 1.0,
      "steps": 8
    },
    {
      "episode": 820,
      "reward": 1.0,
      "steps": 8
    },
    {
      "episode": 821,
      "reward": 1.0,
      "steps": 8
    },
    {
      "episode": 822,
      "reward": 1.0,
      "steps": 8
    },
    {
      "episode": 823,
      "reward": 1.0,
      "steps": 8
    },
    {
      "episode": 824,
      "reward": 1.0,
      "steps": 8
    },
    {
      "episode": 825,
      "reward": 1.0,
      "steps": 8
    },
    {
      "episode": 826,
      "reward": 1.0,
      "steps": 8
    },
    {
      "episode": 827,
      "reward": 1.0,
      "steps": 8
    },
    {
      "episode": 828,
      "reward": 1.0,
      "steps": 12
    },
    {
      "episode": 829,
      "reward": 1.0,
      "steps": 8
    },
    {
      "episode": 830,
      "reward": 1.0,
      "steps": 8
    },
    {
      "episode": 831,
      "reward": 1.0,
      "steps": 8
    },
    {
      "episode": 832,
      "reward": 1.0,
      "steps": 9
    },
    {
      "episode": 833,
      "reward": 1.0,
      "steps": 8
    },
    {
      "episode": 834,
      "reward": 1.0,
      "steps": 8
    },
    {
      "episode": 835,
      "reward": 1.0,
      "steps": 10
    },
    {
      "episode": 836,
      "reward": 1.0,
      "steps": 8
    },
    {
      "episode": 837,
      "reward": 1.0,
      "steps": 8
    },
    {
      "episode": 838,
      "reward": 1.0,
      "steps": 8
    },
    {
      "episode": 839,
      "reward": 1.0,
      "steps": 8
    },
    {
      "episode": 840,
      "reward": 1.0,
      "steps": 12
    },
    {
      "episode": 841,
      "reward": 1.0,
      "steps": 8
    },
    {
      "episode": 842,
      "reward": 1.0,
      "steps": 8
    },
    {
      "episode": 843,
      "reward": 1.0,
      "steps": 8
    },
    {
      "episode": 844,
      "reward": 1.0,
      "steps": 8
    },
    {
      "episode": 845,
      "reward": 1.0,
      "steps": 8
    },
    {
      "episode": 846,
      "reward": 1.0,
      "steps": 10
    },
    {
      "episode": 847,
      "reward": 1.0,
      "steps": 8
    },
    {
      "episode": 848,
      "reward": 1.0,
      "steps": 8
    },
    {
      "episode": 849,
      "reward": 1.0,
      "steps": 8
    },
    {
      "episode": 850,
      "reward": 1.0,
      "steps": 8
    },
    {
      "episode": 851,
      "reward": 1.0,
      "steps": 8
    },
    {
      "episode": 852,
      "reward": 1.0,
      "steps": 8
    },
    {
      "episode": 853,
      "reward": 1.0,
      "steps": 8
    },
    {
      "episode": 854,
      "reward": 1.0,
      "steps": 10
    },
    {
      "episode": 855,
      "reward": 1.0,
      "steps": 8
    },
    {
      "episode": 856,
      "reward": 1.0,
      "steps": 8
    },
    {
      "episode": 857,
      "reward": 1.0,
      "steps": 8
    },
    {
      "episode": 858,
      "reward": 1.0,
      "steps": 10
    },
    {
      "episode": 859,
      "reward": 1.0,
      "steps": 8
    },
    {
      "episode": 860,
      "reward": 1.0,
      "steps": 8
    },
    {
      "episode": 861,
      "reward": 1.0,
      "steps": 8
    },
    {
      "episode": 862,
      "reward": 1.0,
      "steps": 8
    },
    {
      "episode": 863,
      "reward": 1.0,
      "steps": 8
    },
    {
      "episode": 864,
      "reward": 1.0,
      "steps": 10
    },
    {
      "episode": 865,
      "reward": 1.0,
      "steps": 8
    },
    {
      "episode": 866,
      "reward": 1.0,
      "steps": 8
    },
    {
      "episode": 867,
      "reward": 1.0,
      "steps": 8
    },
    {
      "episode": 868,
      "reward": 1.0,
      "steps": 8
    },
    {
      "episode": 869,
      "reward": 1.0,
      "steps": 8
    },
    {
      "episode": 870,
      "reward": 1.0,
      "steps": 9
    },
    {
      "episode": 871,
      "reward": 1.0,
      "steps": 8
    },
    {
      "episode": 872,
      "reward": 1.0,
      "steps": 8
    },
    {
      "episode": 873,
      "reward": 1.0,
      "steps": 8
    },
    {
      "episode": 874,
      "reward": 1.0,
      "steps": 8
    },
    {
      "episode": 875,
      "reward": 1.0,
      "steps": 8
    },
    {
      "episode": 876,
      "reward": 1.0,
      "steps": 11
    },
    {
      "episode": 877,
      "reward": 1.0,
      "steps": 8
    },
    {
      "episode": 878,
      "reward": 1.0,
      "steps": 8
    },
    {
      "episode": 879,
      "reward": 1.0,
      "steps": 8
    },
    {
      "episode": 880,
      "reward": 1.0,
      "steps": 8
    },
    {
      "episode": 881,
      "reward": 1.0,
      "steps": 8
    },
    {
      "episode": 882,
      "reward": 1.0,
      "steps": 8
    },
    {
      "episode": 883,
      "reward": 1.0,
      "steps": 8
    },
    {
      "episode": 884,
      "reward": 1.0,
      "steps": 8
    },
    {
      "episode": 885,
      "reward": 1.0,
      "steps": 8
    },
    {
      "episode": 886,
      "reward": 1.0,
      "steps": 8
    },
    {
      "episode": 887,
      "reward": 1.0,
      "steps": 8
    },
    {
      "episode": 888,
      "reward": 1.0,
      "steps": 8
    },
    {
      "episode": 889,
      "reward": 1.0,
      "steps": 10
    },
    {
      "episode": 890,
      "reward": 1.0,
      "steps": 10
    },
    {
      "episode": 891,
      "reward": 1.0,
      "steps": 8
    },
    {
      "episode": 892,
      "reward": 1.0,
      "steps": 8
    },
    {
      "episode": 893,
      "reward": 1.0,
      "steps": 8
    },
    {
      "episode": 894,
      "reward": 1.0,
      "steps": 8
    },
    {
      "episode": 895,
      "reward": 1.0,
      "steps": 8
    },
    {
      "episode": 896,
      "reward": 1.0,
      "steps": 10
    },
    {
      "episode": 897,
      "reward": 1.0,
      "steps": 9
    },
    {
      "episode": 898,
      "reward": 1.0,
      "steps": 8
    },
    {
      "episode": 899,
      "reward": 1.0,
      "steps": 8
    },
    {
      "episode": 900,
      "reward": 1.0,
      "steps": 8
    },
    {
      "episode": 901,
      "reward": 1.0,
      "steps": 8
    },
    {
      "episode": 902,
      "reward": 1.0,
      "steps": 8
    },
    {
      "episode": 903,
      "reward": 1.0,
      "steps": 8
    },
    {
      "episode": 904,
      "reward": 1.0,
      "steps": 8
    },
    {
      "episode": 905,
      "reward": 1.0,
      "steps": 8
    },
    {
      "episode": 906,
      "reward": 1.0,
      "steps": 8
    },
    {
      "episode": 907,
      "reward": 1.0,
      "steps": 8
    },
    {
      "episode": 908,
      "reward": 1.0,
      "steps": 8
    },
    {
      "episode": 909,
      "reward": 1.0,
      "steps": 8
    },
    {
      "episode": 910,
      "reward": 1.0,
      "steps": 8
    },
    {
      "episode": 911,
      "reward": 1.0,
      "steps": 9
    },
    {
      "episode": 912,
      "reward": 1.0,
      "steps": 8
    },
    {
      "episode": 913,
      "reward": 1.0,
      "steps": 8
    },
    {
      "episode": 914,
      "reward": 1.0,
      "steps": 8
    },
    {
      "episode": 915,
      "reward": 1.0,
      "steps": 8
    },
    {
      "episode": 916,
      "reward": 1.0,
      "steps": 8
    },
    {
      "episode": 917,
      "reward": 1.0,
      "steps": 8
    },
    {
      "episode": 918,
      "reward": 1.0,
      "steps": 8
    },
    {
      "episode": 919,
      "reward": 1.0,
      "steps": 10
    },
    {
      "episode": 920,
      "reward": 1.0,
      "steps": 8
    },
    {
      "episode": 921,
      "reward": 1.0,
      "steps": 8
    },
    {
      "episode": 922,
      "reward": 1.0,
      "steps": 8
    },
    {
      "episode": 923,
      "reward": 1.0,
      "steps": 8
    },
    {
      "episode": 924,
      "reward": 1.0,
      "steps": 8
    },
    {
      "episode": 925,
      "reward": 1.0,
      "steps": 8
    },
    {
      "episode": 926,
      "reward": 1.0,
      "steps": 8
    },
    {
      "episode": 927,
      "reward": 1.0,
      "steps": 8
    },
    {
      "episode": 928,
      "reward": 1.0,
      "steps": 8
    },
    {
      "episode": 929,
      "reward": 1.0,
      "steps": 10
    },
    {
      "episode": 930,
      "reward": 1.0,
      "steps": 8
    },
    {
      "episode": 931,
      "reward": 1.0,
      "steps": 8
    },
    {
      "episode": 932,
      "reward": 1.0,
      "steps": 8
    },
    {
      "episode": 933,
      "reward": 1.0,
      "steps": 8
    },
    {
      "episode": 934,
      "reward": 1.0,
      "steps": 8
    },
    {
      "episode": 935,
      "reward": 1.0,
      "steps": 8
    },
    {
      "episode": 936,
      "reward": 1.0,
      "steps": 8
    },
    {
      "episode": 937,
      "reward": 1.0,
      "steps": 8
    },
    {
      "episode": 938,
      "reward": 1.0,
      "steps": 8
    },
    {
      "episode": 939,
      "reward": 1.0,
      "steps": 10
    },
    {
      "episode": 940,
      "reward": 1.0,
      "steps": 8
    },
    {
      "episode": 941,
      "reward": 1.0,
      "steps": 8
    },
    {
      "episode": 942,
      "reward": 1.0,
      "steps": 8
    },
    {
      "episode": 943,
      "reward": 1.0,
      "steps": 8
    },
    {
      "episode": 944,
      "reward": 1.0,
      "steps": 8
    },
    {
      "episode": 945,
      "reward": 1.0,
      "steps": 8
    },
    {
      "episode": 946,
      "reward": 1.0,
      "steps": 12
    },
    {
      "episode": 947,
      "reward": 1.0,
      "steps": 8
    },
    {
      "episode": 948,
      "reward": 1.0,
      "steps": 10
    },
    {
      "episode": 949,
      "reward": 1.0,
      "steps": 8
    },
    {
      "episode": 950,
      "reward": 1.0,
      "steps": 8
    },
    {
      "episode": 951,
      "reward": 1.0,
      "steps": 8
    },
    {
      "episode": 952,
      "reward": 1.0,
      "steps": 8
    },
    {
      "episode": 953,
      "reward": 1.0,
      "steps": 8
    },
    {
      "episode": 954,
      "reward": 1.0,
      "steps": 8
    },
    {
      "episode": 955,
      "reward": 1.0,
      "steps": 8
    },
    {
      "episode": 956,
      "reward": 1.0,
      "steps": 8
    },
    {
      "episode": 957,
      "reward": 1.0,
      "steps": 8
    },
    {
      "episode": 958,
      "reward": 1.0,
      "steps": 8
    },
    {
      "episode": 959,
      "reward": 1.0,
      "steps": 9
    },
    {
      "episode": 960,
      "reward": 1.0,
      "steps": 10
    },
    {
      "episode": 961,
      "reward": 1.0,
      "steps": 10
    },
    {
      "episode": 962,
      "reward": 1.0,
      "steps": 8
    },
    {
      "episode": 963,
      "reward": 1.0,
      "steps": 8
    },
    {
      "episode": 964,
      "reward": 1.0,
      "steps": 8
    },
    {
      "episode": 965,
      "reward": 1.0,
      "steps": 8
    },
    {
      "episode": 966,
      "reward": 1.0,
      "steps": 8
    },
    {
      "episode": 967,
      "reward": 1.0,
      "steps": 8
    },
    {
      "episode": 968,
      "reward": 1.0,
      "steps": 8
    },
    {
      "episode": 969,
      "reward": 1.0,
      "steps": 8
    },
    {
      "episode": 970,
      "reward": 1.0,
      "steps": 8
    },
    {
      "episode": 971,
      "reward": 1.0,
      "steps": 8
    },
    {
      "episode": 972,
      "reward": 1.0,
      "steps": 8
    },
    {
      "episode": 973,
      "reward": 1.0,
      "steps": 9
    },
    {
      "episode": 974,
      "reward": 1.0,
      "steps": 8
    },
    {
      "episode": 975,
      "reward": 1.0,
      "steps": 8
    },
    {
      "episode": 976,
      "reward": 1.0,
      "steps": 8
    },
    {
      "episode": 977,
      "reward": 1.0,
      "steps": 10
    },
    {
      "episode": 978,
      "reward": 1.0,
      "steps": 8
    },
    {
      "episode": 979,
      "reward": 1.0,
      "steps": 8
    },
    {
      "episode": 980,
      "reward": 1.0,
      "steps": 8
    },
    {
      "episode": 981,
      "reward": 1.0,
      "steps": 8
    },
    {
      "episode": 982,
      "reward": 1.0,
      "steps": 8
    },
    {
      "episode": 983,
      "reward": 1.0,
      "steps": 8
    },
    {
      "episode": 984,
      "reward": 1.0,
      "steps": 8
    },
    {
      "episode": 985,
      "reward": 1.0,
      "steps": 8
    },
    {
      "episode": 986,
      "reward": 1.0,
      "steps": 8
    },
    {
      "episode": 987,
      "reward": 1.0,
      "steps": 8
    },
    {
      "episode": 988,
      "reward": 1.0,
      "steps": 8
    },
    {
      "episode": 989,
      "reward": 1.0,
      "steps": 8
    },
    {
      "episode": 990,
      "reward": 1.0,
      "steps": 8
    },
    {
      "episode": 991,
      "reward": 1.0,
      "steps": 10
    },
    {
      "episode": 992,
      "reward": 1.0,
      "steps": 8
    },
    {
      "episode": 993,
      "reward": 1.0,
      "steps": 8
    },
    {
      "episode": 994,
      "reward": 1.0,
      "steps": 8
    },
    {
      "episode": 995,
      "reward": 1.0,
      "steps": 8
    },
    {
      "episode": 996,
      "reward": 1.0,
      "steps": 8
    },
    {
      "episode": 997,
      "reward": 1.0,
      "steps": 8
    },
    {
      "episode": 998,
      "reward": 1.0,
      "steps": 8
    },
    {
      "episode": 999,
      "reward": 1.0,
      "steps": 8
    },
    {
      "episode": 1000,
      "reward": 1.0,
      "steps": 10
    }
  ]
}